src/AudioPy/AudioAi.py
src/AudioPy/__init__.py
audioai-1.2.2.dist-info/METADATA
audioai-1.2.2.dist-info/WHEEL
audioai-1.2.2.dist-info/licenses/LICENSE
audioai-1.2.2.dist-info/RECORD
